CHANGES.txt
CONTRIBUTORS.txt
MANIFEST.in
README.rst
setup.py
docs/HISTORY.txt
docs/INSTALL.txt
docs/LICENSE.GPL
docs/LICENSE.txt
docs/UPGRADING.txt
uwosh/__init__.py
uwosh.pfg.d2c.egg-info/PKG-INFO
uwosh.pfg.d2c.egg-info/SOURCES.txt
uwosh.pfg.d2c.egg-info/dependency_links.txt
uwosh.pfg.d2c.egg-info/entry_points.txt
uwosh.pfg.d2c.egg-info/namespace_packages.txt
uwosh.pfg.d2c.egg-info/not-zip-safe
uwosh.pfg.d2c.egg-info/requires.txt
uwosh.pfg.d2c.egg-info/top_level.txt
uwosh/pfg/__init__.py
uwosh/pfg/d2c/__init__.py
uwosh/pfg/d2c/browser.txt
uwosh/pfg/d2c/config.py
uwosh/pfg/d2c/configure.zcml
uwosh/pfg/d2c/events.py
uwosh/pfg/d2c/exportimport.py
uwosh/pfg/d2c/extender.py
uwosh/pfg/d2c/folderutils.py
uwosh/pfg/d2c/index.txt
uwosh/pfg/d2c/interfaces.py
uwosh/pfg/d2c/tests.py
uwosh/pfg/d2c/upgrades.py
uwosh/pfg/d2c/upgrades.zcml
uwosh/pfg/d2c/utils.py
uwosh/pfg/d2c/version.txt
uwosh/pfg/d2c/widgets.py
uwosh/pfg/d2c/browser/__init__.py
uwosh/pfg/d2c/browser/configure.zcml
uwosh/pfg/d2c/browser/utils.py
uwosh/pfg/d2c/content/__init__.py
uwosh/pfg/d2c/content/configure.zcml
uwosh/pfg/d2c/content/dataentry.py
uwosh/pfg/d2c/content/savedataadapter.py
uwosh/pfg/d2c/locales/rebuild.sh
uwosh/pfg/d2c/locales/uwosh.pfg.d2c-manual.pot
uwosh/pfg/d2c/locales/uwosh.pfg.d2c.pot
uwosh/pfg/d2c/locales/fi/LC_MESSAGES/uwosh.pfg.d2c.mo
uwosh/pfg/d2c/locales/fi/LC_MESSAGES/uwosh.pfg.d2c.po
uwosh/pfg/d2c/locales/it/LC_MESSAGES/uwosh.pfg.d2c.mo
uwosh/pfg/d2c/locales/it/LC_MESSAGES/uwosh.pfg.d2c.po
uwosh/pfg/d2c/profiles/default/browserlayer.xml
uwosh/pfg/d2c/profiles/default/factorytool.xml
uwosh/pfg/d2c/profiles/default/import_steps.xml
uwosh/pfg/d2c/profiles/default/jsregistry.xml
uwosh/pfg/d2c/profiles/default/metadata.xml
uwosh/pfg/d2c/profiles/default/skins.xml
uwosh/pfg/d2c/profiles/default/types.xml
uwosh/pfg/d2c/profiles/default/uwosh.pfg.d2c.txt
uwosh/pfg/d2c/profiles/default/types/FormSaveData2ContentAdapter.xml
uwosh/pfg/d2c/profiles/default/types/FormSaveData2ContentEntry.xml
uwosh/pfg/d2c/skins/uwosh_pfg_d2c_templates/d2c-adapter-selection.pt
uwosh/pfg/d2c/skins/uwosh_pfg_d2c_templates/d2c-edit.js
uwosh/pfg/d2c/skins/uwosh_pfg_d2c_templates/donationfield_widget.pt
uwosh/pfg/d2c/skins/uwosh_pfg_d2c_templates/widget_likert.pt