Metadata-Version: 1.1
Name: uwosh.pfg.d2c
Version: 2.4.6
Summary: A PloneFormGen adapter that will save the data from a form to an actual content type. This way you can still use permissions, workflows, etc on the form data.
Home-page: http://pypi.python.org/pypi/uwosh.pfg.d2c
Author: Nathan Van Gheem
Author-email: vangheem@gmail.com
License: GPL
Keywords: ploneformgen plone forms adapter uwosh
Platform: UNKNOWN
Classifier: Framework :: Plone
Classifier: Intended Audience :: Developers
Classifier: License :: OSI Approved :: GNU General Public License (GPL)
